geoz.py
geoz-2.0.1.dist-info/LICENSE
geoz-2.0.1.dist-info/METADATA
geoz-2.0.1.dist-info/WHEEL
geoz-2.0.1.dist-info/top_level.txt
geoz-2.0.1.dist-info/RECORD
