Metadata-Version: 2.1
Name: geoz
Version: 2.0.1
Summary: A Library to convert Unsupervised Clustering Results into Geographical Maps
Home-page: https://github.com/Ne-oL/geoz
Author: Khalid ElHaj
Author-email: KG.Khair@Gmail.com
License: BSD 3-Clause
Classifier: Programming Language :: Python :: 3
Classifier: Programming Language :: Python :: 3.9
Classifier: Topic :: Scientific/Engineering :: Artificial Intelligence
Classifier: Topic :: Scientific/Engineering :: GIS
Classifier: Topic :: Scientific/Engineering :: Visualization
Classifier: License :: OSI Approved :: BSD License
Classifier: Operating System :: OS Independent
Requires-Python: >=3
License-File: LICENSE
Requires-Dist: pandas
Requires-Dist: mlxtend
Requires-Dist: scikit-learn
Requires-Dist: matplotlib
Requires-Dist: geopandas
Requires-Dist: shapely
Provides-Extra: dev
Requires-Dist: pytest>=3.9; extra == "dev"
Requires-Dist: check-manifest; extra == "dev"
Requires-Dist: twine; extra == "dev"
